{
  "receipts": [
    {
      "id": 1,
      "date": "2021-08-02 00:00:00",
      "userName": "孙六",
      "province": 2,
      "city": "普陀区",
      "address": "金沙江路 1518弄",
      "zip": 200000
    },
    {
      "id": 2,
      "date": "2022-08-03 00:00:00",
      "userName": "张三",
      "province": 1,
      "city": "朝阳区",
      "address": "王府井大街56号",
      "zip": "100000"
    },
    {
      "id": 3,
      "date": "2022-08-03 00:00:00",
      "userName": "李四",
      "province": 4,
      "city": "南京市玄武区",
      "address": "望海路33号",
      "zip": 518000
    },
    {
      "id": 4,
      "date": "2022-08-03 16:00:00",
      "userName": "王五",
      "province": 3,
      "city": "广州白云区",
      "address": "白云路100号",
      "zip": 510000
    },
    {
      "date": "2022-08-03 16:00:00",
      "userName": "Demo",
      "province": 2,
      "city": "吴淞区",
      "address": "省去20个字...",
      "zip": "210000",
      "id": 5
    },
    {
      "date": "2022-08-04 00:00:00",
      "userName": "Sample",
      "province": 3,
      "city": "深圳南山区",
      "address": "省去20个字...",
      "zip": "210000",
      "id": 6
    },
    {
      "date": "2022-08-01 00:00:00",
      "userName": "艾纽",
      "province": 2,
      "city": "宝山区",
      "address": "省去20个字...",
      "zip": "210000",
      "id": 7
    },
    {
      "date": "2022-08-06 00:00:00",
      "userName": "haha",
      "province": 1,
      "city": "海淀区",
      "address": "中关村5#",
      "zip": "100005",
      "id": 8
    },
    {
      "date": "2022-08-05 00:00:00",
      "userName": "GG",
      "province": 1,
      "city": "朝阳区",
      "address": "省去20个字...",
      "zip": "100000",
      "id": 9
    },
    {
      "date": "2022-08-06 00:00:00",
      "userName": "AA",
      "province": 2,
      "city": "闵行区",
      "address": "省去20个字...",
      "zip": "210000",
      "id": 10
    },
    {
      "date": "2022-08-05 00:00:00",
      "userName": "KK",
      "province": 3,
      "city": "深圳市福田",
      "address": "省去20个字...",
      "zip": "518000",
      "id": 11
    }
  ]
}
